clg/conf/__init__.py
clg/conf/src.py
clg_conf-1.0.0.dist-info/LICENSE
clg_conf-1.0.0.dist-info/METADATA
clg_conf-1.0.0.dist-info/WHEEL
clg_conf-1.0.0.dist-info/top_level.txt
clg_conf-1.0.0.dist-info/RECORD
