Metadata-Version: 2.1
Name: clg-conf
Version: 1.0.0
Summary: Manage per command configuration files.
Home-page: http://github.com/fmenabe/python-clg-conf
Download-URL: http://github.com/fmenabe/python-clg-conf
Author: François Ménabé
Author-email: francois.menabe@gmail.com
License: MIT License
Keywords: command-line,argparse,wrapper,clg
Classifier: Development Status :: 3 - Alpha
Classifier: Environment :: Console
Classifier: Intended Audience :: Developers
Classifier: Intended Audience :: System Administrators
Classifier: License :: OSI Approved :: MIT License
Classifier: Programming Language :: Python
Classifier: Programming Language :: Python :: 2.7
Classifier: Programming Language :: Python :: 3.4
Classifier: Programming Language :: Python :: 3.5
Classifier: Topic :: Utilities
License-File: LICENSE
Requires-Dist: clg
Requires-Dist: addict
